uniswap_v3_quoter/__init__.py
uniswap_v3_quoter/quoter.py
uniswap_v3_quoter/setup.py
uniswap_v3_quoter/state/__init__.py
uniswap_v3_quoter/state/pool_state.py
uniswap_v3_quoter/state/state_fetcher.py
uniswap_v3_quoter/state/ws_subscriber.py
uniswap_v3_quoter/uniswap_math/__init__.py
uniswap_v3_quoter/uniswap_math/full_math.py
uniswap_v3_quoter/uniswap_math/liquidity_math.py
uniswap_v3_quoter/uniswap_math/sqrt_price_math.py
uniswap_v3_quoter/uniswap_math/swap_math.py
uniswap_v3_quoter/uniswap_math/tick_bitmap.py
uniswap_v3_quoter/uniswap_math/tick_math.py
uniswap_v3_quoter-1.0.6.dist-info/licenses/LICENSE
uniswap_v3_quoter-1.0.6.dist-info/METADATA
uniswap_v3_quoter-1.0.6.dist-info/WHEEL
uniswap_v3_quoter-1.0.6.dist-info/top_level.txt
uniswap_v3_quoter-1.0.6.dist-info/RECORD
