Metadata-Version: 2.4
Name: uniswap-v3-quoter
Version: 1.0.6
Summary: Python implementation of Uniswap V3 QuoterV2 for high-frequency trading
Home-page: https://github.com/yourusername/v3-python-quoter
Author: V3 Python Quoter Contributors
License-Expression: MIT
Project-URL: Homepage, https://github.com/yourusername/v3-python-quoter
Project-URL: Documentation, https://github.com/yourusername/v3-python-quoter/blob/main/README.md
Project-URL: Repository, https://github.com/yourusername/v3-python-quoter
Project-URL: Bug Tracker, https://github.com/yourusername/v3-python-quoter/issues
Keywords: uniswap,uniswap-v3,pancakeswap,defi,dex,quoter,trading,ethereum,bsc,web3
Classifier: Development Status :: 4 - Beta
Classifier: Intended Audience :: Developers
Classifier: Intended Audience :: Financial and Insurance Industry
Classifier: Programming Language :: Python :: 3
Classifier: Programming Language :: Python :: 3.8
Classifier: Programming Language :: Python :: 3.9
Classifier: Programming Language :: Python :: 3.10
Classifier: Programming Language :: Python :: 3.11
Classifier: Programming Language :: Python :: 3.12
Classifier: Topic :: Office/Business :: Financial
Classifier: Topic :: Software Development :: Libraries :: Python Modules
Requires-Python: >=3.8
License-File: LICENSE
Requires-Dist: web3>=6.0.0
Requires-Dist: eth-abi>=4.0.0
Requires-Dist: eth-utils>=2.0.0
Requires-Dist: eth-typing>=3.0.0
Provides-Extra: dev
Requires-Dist: pytest>=7.0.0; extra == "dev"
Requires-Dist: pytest-cov>=4.0.0; extra == "dev"
Requires-Dist: black>=23.0.0; extra == "dev"
Requires-Dist: ruff>=0.1.0; extra == "dev"
Requires-Dist: mypy>=1.0.1; extra == "dev"
Provides-Extra: performance
Requires-Dist: orjson>=3.9.0; extra == "performance"
Requires-Dist: cytoolz>=0.12.0; extra == "performance"
Dynamic: home-page
Dynamic: license-file
Dynamic: requires-python
